bothub_cli/__init__.py
bothub_cli/api.py
bothub_cli/clients.py
bothub_cli/config.py
bothub_cli/exceptions.py
bothub_cli/lib.py
bothub_cli/main.py
bothub_cli/template.py
bothub_cli/utils.py
bothub_cli-0.1.20.dist-info/METADATA
bothub_cli-0.1.20.dist-info/RECORD
bothub_cli-0.1.20.dist-info/WHEEL
bothub_cli-0.1.20.dist-info/entry_points.txt
bothub_cli-0.1.20.dist-info/top_level.txt
