Metadata-Version: 2.1
Name: bothub-cli
Version: 0.1.20
Summary: A CLI tool for bothub.studio service
Home-page: https://github.com/bothub-studio/bothub-cli
Author: Jeongsoo Park
Author-email: jeongsoo.park@bothub.studio
License: Apache 2.0
Keywords: bothub serverless chatbot framework cli
Platform: UNKNOWN
Classifier: Development Status :: 3 - Alpha
Classifier: Intended Audience :: Developers
Classifier: Operating System :: OS Independent
Classifier: License :: OSI Approved :: Apache Software License
Classifier: Programming Language :: Python
Classifier: Programming Language :: Python :: 2
Classifier: Programming Language :: Python :: 3
Classifier: Topic :: Communications :: Chat
Classifier: Topic :: Software Development :: Libraries :: Application Frameworks
Classifier: Topic :: Utilities
Requires-Dist: six
Requires-Dist: click
Requires-Dist: requests
Requires-Dist: pyyaml
Requires-Dist: pyjwt
Requires-Dist: terminaltables
Requires-Dist: prompt-toolkit (>=2.0)
Requires-Dist: bothub (>=0.1.18)
Requires-Dist: pathspec
Requires-Dist: dialogflow
Requires-Dist: ruamel.yaml
